django_jsonsuit-0.4.4.dist-info/DESCRIPTION.rst
django_jsonsuit-0.4.4.dist-info/METADATA
django_jsonsuit-0.4.4.dist-info/RECORD
django_jsonsuit-0.4.4.dist-info/WHEEL
django_jsonsuit-0.4.4.dist-info/metadata.json
django_jsonsuit-0.4.4.dist-info/top_level.txt
jsonsuit/__init__.py
jsonsuit/app_settings.py
jsonsuit/apps.py
jsonsuit/models.py
jsonsuit/urls.py
jsonsuit/widgets.py
jsonsuit/static/jsonsuit/css/jsonsuit.css
jsonsuit/static/jsonsuit/css/prism-coy.css
jsonsuit/static/jsonsuit/css/prism-dark.css
jsonsuit/static/jsonsuit/css/prism-default.css
jsonsuit/static/jsonsuit/css/prism-funky.css
jsonsuit/static/jsonsuit/css/prism-okaidia.css
jsonsuit/static/jsonsuit/css/prism-solarizedlight.css
jsonsuit/static/jsonsuit/css/prism-twilight.css
jsonsuit/static/jsonsuit/js/jsonsuit.js
jsonsuit/static/jsonsuit/js/prism.js
jsonsuit/static/jsonsuit/js/readonly-jsonsuit.js
jsonsuit/templates/jsonsuit/base.html
jsonsuit/templates/jsonsuit/readonly_widget.html
jsonsuit/templates/jsonsuit/widget.html
jsonsuit/templatetags/__init__.py
jsonsuit/templatetags/jsonsuit.py
